factoriocalc/__init__.py
factoriocalc/_helper.py
factoriocalc/blueprint.py
factoriocalc/box.py
factoriocalc/config.py
factoriocalc/contextvars_.py
factoriocalc/core.py
factoriocalc/data.py
factoriocalc/fracs.py
factoriocalc/game-info-v_1_1-expensive.json
factoriocalc/game-info-v_1_1-normal.json
factoriocalc/game-info-v_2_0-sa.json
factoriocalc/game-info-v_2_0.json
factoriocalc/helper.py
factoriocalc/import_.py
factoriocalc/itm.py
factoriocalc/jsonconv.py
factoriocalc/machine.py
factoriocalc/mch.py
factoriocalc/mods.py
factoriocalc/ordenum.py
factoriocalc/presets.py
factoriocalc/produce.py
factoriocalc/rcp.py
factoriocalc/solver.py
factoriocalc/test_fracs.py
factoriocalc/units.py
factoriocalc-0.3.0.dist-info/LICENSE
factoriocalc-0.3.0.dist-info/METADATA
factoriocalc-0.3.0.dist-info/WHEEL
factoriocalc-0.3.0.dist-info/top_level.txt
factoriocalc-0.3.0.dist-info/RECORD
