Metadata-Version: 2.1
Name: factoriocalc
Version: 0.3.0
Summary: A python module to help you plan your factory for Factorio.
Author: Kevin Atkinson
Project-URL: Homepage, https://github.com/FactorioCalc/FactorioCalc
Project-URL: Bug Tracker, https://github.com/FactorioCalc/FactorioCalc/issues
Keywords: Factorio
Classifier: Programming Language :: Python :: 3
Classifier: Development Status :: 3 - Alpha
Classifier: License :: OSI Approved :: GNU Affero General Public License v3 or later (AGPLv3+)
Classifier: Operating System :: OS Independent
Requires-Python: >=3.7
License-File: LICENSE
